Metadata-Version: 2.4
Name: llm-tools-mcp
Version: 0.3
Summary: MCP support for LLM CLI
Author: Michal Fudala
License-Expression: Apache-2.0
Project-URL: Homepage, https://github.com/VirtusLab/llm-tools-mcp
Project-URL: Changelog, https://github.com/VirtusLab/llm-tools-mcp/releases
Project-URL: Issues, https://github.com/VirtusLab/llm-tools-mcp/issues
Project-URL: CI, https://github.com/VirtusLab/llm-tools-mcp/actions
Requires-Python: >=3.10
License-File: LICENSE
Requires-Dist: llm
Requires-Dist: mcp[cli]>=1.9.1
Requires-Dist: requests>=2.32.3
Provides-Extra: test
Requires-Dist: pytest; extra == "test"
Requires-Dist: pytest-asyncio>=1.0.0; extra == "test"
Requires-Dist: pytest-watch>=4.2.0; extra == "test"
Dynamic: license-file
